lotr_sdk/__init__.py
lotr_sdk/access_token.py
lotr_sdk/books.py
lotr_sdk/chapters.py
lotr_sdk/characters.py
lotr_sdk/init_token.py
lotr_sdk/movies.py
lotr_sdk/quotes.py
lotr_sdk/settings.py
lotr_sdk-0.0.3.dist-info/METADATA
lotr_sdk-0.0.3.dist-info/WHEEL
lotr_sdk-0.0.3.dist-info/top_level.txt
lotr_sdk-0.0.3.dist-info/RECORD
